pyspectator/__init__.py
pyspectator/collection.py
pyspectator/computer.py
pyspectator/convert.py
pyspectator/memory.py
pyspectator/monitoring.py
pyspectator/network.py
pyspectator/processor.py
pyspectator/temperature_reader.py
pyspectator-1.2.2.data/scripts/console.py
pyspectator-1.2.2.dist-info/LICENSE
pyspectator-1.2.2.dist-info/METADATA
pyspectator-1.2.2.dist-info/WHEEL
pyspectator-1.2.2.dist-info/top_level.txt
pyspectator-1.2.2.dist-info/RECORD
